box/__init__.py
box/__read_2.py
box/ai_truncate.py
box/bat.py
box/color.py
box/common.py
box/data.py
box/date.py
box/db.py
box/db_api_base.py
box/dbutils.py
box/error.py
box/error2.py
box/frame.py
box/get.py
box/ic.py
box/introspection.py
box/json_decode_error.py
box/jsonfile.py
box/log.py
box/markup.py
box/null.py
box/peewee_clusters.py
box/print_utils.py
box/reltools.py
box/reqs.py
box/rich_experiments.py
box/table.py
box/tdd.py
box/template.py
box/test.py
box/test_debugger.py
box/test_import.py
box/test_relimport.py
box/test_truncate.py
box/timer.py
box/tmp_peewee_endpoint.py
box/tmp_sqlalchemy_where_to_str.py
box/tmp_sqlite_to_sqlalchemy.py
box/trace.py
box/truncate.py
waivek/__init__.py
waivek/__read_2.py
waivek/ai_truncate.py
waivek/bat.py
waivek/color.py
waivek/common.py
waivek/data.py
waivek/date.py
waivek/db.py
waivek/dbutils.py
waivek/error.py
waivek/error2.py
waivek/frame.py
waivek/get.py
waivek/ic.py
waivek/introspection.py
waivek/json_decode_error.py
waivek/log.py
waivek/markup.py
waivek/null.py
waivek/print_utils.py
waivek/reltools.py
waivek/reqs.py
waivek/table.py
waivek/tdd.py
waivek/template.py
waivek/test.py
waivek/test_debugger.py
waivek/test_import.py
waivek/test_relimport.py
waivek/test_truncate.py
waivek/timer.py
waivek/trace.py
waivek/truncate.py
box-0.1.5.dist-info/METADATA
box-0.1.5.dist-info/WHEEL
box-0.1.5.dist-info/top_level.txt
box-0.1.5.dist-info/RECORD
